MANIFEST.in
Readme.md
requirements.txt
setup.py
hscacheutils/__init__.py
hscacheutils/generational_cache.py
hscacheutils/raw_cache.py
hscacheutils/setting_wrappers.py
hscacheutils/simple_memory_cache.py
hscacheutils.egg-info/PKG-INFO
hscacheutils.egg-info/SOURCES.txt
hscacheutils.egg-info/dependency_links.txt
hscacheutils.egg-info/requires.txt
hscacheutils.egg-info/top_level.txt