Metadata-Version: 1.0
Name: hscacheutils
Version: 0.1.8
Summary: Some of Hubspot's python cache utils, namely generational caching
Home-page: http://dev.hubspot.com/
Author: HubSpot Developer
Author-email: devteam+hscacheutils@hubspot.com
License: MIT
Platform: any
